Workbook
Name Aporte: 'Projeto (DIO)'!$C$16:$D$16
Name Rendimentocarteira: 'Projeto (DIO)'!$C$12:$C$12

Sheet Projeto (DIO)
B10: Configuração
B11: Salário | C11: 5000
B12: Rendimento da carteira | C12: 0.006
B13: Sugestão de investimento (30%) | C13: =C11*30% -> 1500
B15: Investimento Mensal
B16: Quanto investir por mês ? | C16: 100
B17: Por Quantos Anos ? | C17: 5
B18: Taxa de Rendimento mensal ? | C18: 0.01079
B19: Patrimônio acumulado ? | C19: =FV(C18,C17*12,C16*-1) -> 8377.6914
B20: Dividendos Mensais ? | C20: =(C19*C18) -> 90.39529
B22: Cenários | E22: Dividendos
B23: Quanto em 2 anos? | C23: =FV(C18,2*12,C16*-1) -> 2722.7627 | E23: =C23*C12 -> 16.336576
B24: Quanto em 5 anos? | C24: =FV(C18,5*12,C16*-1) -> 8377.6914 | E24: =C24*$C$12 -> 50.266148
B25: Quanto em 10 anos? | C25: =FV(C18,10*12,C16*-1) -> 24328.421 | E25: =C25*$C$12 -> 145.97053
B26: Quanto em 20 anos? | C26: =FV(C18,20*12,C16*-1) -> 112519.84 | E26: =C26*$C$12 -> 675.11904
B27: Quanto em 30 anos ? | C27: =FV(C18,30*12,C16*-1) -> 432216.97 | E27: =C27*$C$12 -> 2593.3018
B30: Perfil | D30: Moderado
E31: 500
B32: Tipo de FI | C32: Percentual sugerido | E32: Valores
B33: Papel | C33: =VLOOKUP($D$30&"-"&B33,Planilha1!A1:D23,4,FALSE) -> 0.35 | E33: =C33*$E$31 -> 175
B34: Tijolo | C34: =VLOOKUP($D$30&"-"&B34,Planilha1!A2:D24,4,FALSE) -> 0.32 | E34: =C34*$E$31 -> 160
B35: Híbridos | C35: =VLOOKUP($D$30&"-"&B35,Planilha1!A3:D25,4,FALSE) -> 0.08 | D35: -Híbridos"; Planilha1!$A$2:$E$7; 4; FALSO) | E35: =C35*$E$31 -> 40
B36: FOFs | C36: =VLOOKUP($D$30&"-"&B36,Planilha1!A4:D26,4,FALSE) -> 0.05 | E36: =C36*$E$31 -> 25
B37: Desenvolvimento | C37: =VLOOKUP($D$30&"-"&B37,Planilha1!A5:D27,4,FALSE) -> 0.1 | E37: =C37*$E$31 -> 50
B38: Hotelarias | C38: =VLOOKUP($D$30&"-"&B38,Planilha1!A6:D28,4,FALSE) -> 0.1 | E38: =C38*$E$31 -> 50
E39: =C3+E34+E35+E36+E37+E38+E33 -> 500

Sheet Planilha1
A1: Chave composto | B1: Perfil | C1: Perfil de Fii | D1: %
A2: Conservador-Papel | B2: Conservador | C2: Papel | D2: 0.3
A3: Conservador-Tijolo | B3: Conservador | C3: Tijolo | D3: 0.5
A4: Conservador-Híbridos | B4: Conservador | C4: Híbridos | D4: 0.1
A5: Conservador-FOFs | B5: Conservador | C5: FOFs | D5: 0.1
A6: Conservador-Desenvolvimento | B6: Conservador | C6: Desenvolvimento | D6: 0
A7: Conservador-Hotelarias | B7: Conservador | C7: Hotelarias | D7: 0 | H7: =A11 -> Moderado-Tijolo | J7: =VLOOKUP(H7,A1:D23,4,FALSE) -> 0.32
A9: Chave composto | B9: Perfil | C9: Perfil de Fii
A10: =B10&"-"&C10 -> Moderado-Papel | B10: Moderado | C10: Papel | D10: 0.35
A11: =B11&"-"&C11 -> Moderado-Tijolo | B11: Moderado | C11: Tijolo | D11: 0.32
A12: =B12&"-"&C12 -> Moderado-Híbridos | B12: Moderado | C12: Híbridos | D12: 0.08
A13: =B13&"-"&C13 -> Moderado-FOFs | B13: Moderado | C13: FOFs | D13: 0.05
A14: =B14&"-"&C14 -> Moderado-Desenvolvimento | B14: Moderado | C14: Desenvolvimento | D14: 0.1
A15: =B15&"-"&C15 -> Moderado-Hotelarias | B15: Moderado | C15: Hotelarias | D15: 0.1
A17: Chave composto | B17: Perfil | C17: Perfil de Fii
A18: =B18&"-"&C18 -> Agressivo-Papel | B18: Agressivo | C18: Papel | D18: 0.5
A19: =B19&"-"&C19 -> Agressivo-Tijolo | B19: Agressivo | C19: Tijolo | D19: 0.1
A20: =B20&"-"&C20 -> Agressivo-Híbridos | B20: Agressivo | C20: Híbridos | D20: 0.05
A21: =B21&"-"&C21 -> Agressivo-FOFs | B21: Agressivo | C21: FOFs | D21: 0.05
A22: =B22&"-"&C22 -> Agressivo-Desenvolvimento | B22: Agressivo | C22: Desenvolvimento | D22: 0.2
A23: =B23&"-"&C23 -> Agressivo-Hotelarias | B23: Agressivo | C23: Hotelarias | D23: 0.1
